{
    "key": "group_6217d77365e39",
    "title": "Event ACF",
    "fields": [
        {
            "key": "field_6217d773696e7",
            "label": "Event Title",
            "name": "event_title",
            "type": "text",
            "instructions": "",
            "required": 0,
            "conditional_logic": 0,
            "wrapper": {
                "width": "",
                "class": "",
                "id": ""
            },
            "default_value": "",
            "placeholder": "",
            "prepend": "",
            "append": "",
            "maxlength": "",
            "acfe_field_group_condition": 0
        },
        {
            "key": "field_6217d77369738",
            "label": "Titre de l'événement",
            "name": "event_title_fr",
            "type": "text",
            "instructions": "",
            "required": 0,
            "conditional_logic": 0,
            "wrapper": {
                "width": "",
                "class": "",
                "id": ""
            },
            "default_value": "",
            "placeholder": "",
            "prepend": "",
            "append": "",
            "maxlength": "",
            "acfe_field_group_condition": 0
        },
        {
            "key": "field_6217d7736977c",
            "label": "Abstract",
            "name": "event_abstract",
            "type": "wysiwyg",
            "instructions": "",
            "required": 0,
            "conditional_logic": 0,
            "wrapper": {
                "width": "",
                "class": "",
                "id": ""
            },
            "default_value": "",
            "tabs": "all",
            "toolbar": "full",
            "media_upload": 1,
            "delay": 0,
            "acfe_wysiwyg_height": 300,
            "acfe_wysiwyg_max_height": "",
            "acfe_wysiwyg_valid_elements": "",
            "acfe_wysiwyg_custom_style": "",
            "acfe_wysiwyg_disable_wp_style": 0,
            "acfe_wysiwyg_autoresize": 0,
            "acfe_wysiwyg_disable_resize": 0,
            "acfe_wysiwyg_remove_path": 0,
            "acfe_wysiwyg_menubar": 0,
            "acfe_wysiwyg_transparent": 0,
            "acfe_wysiwyg_merge_toolbar": 0,
            "acfe_wysiwyg_custom_toolbar": 0,
            "acfe_field_group_condition": 0
        },
        {
            "key": "field_6217d773697c6",
            "label": "Résumé de l'événement",
            "name": "event_abstract_fr",
            "type": "wysiwyg",
            "instructions": "",
            "required": 0,
            "conditional_logic": 0,
            "wrapper": {
                "width": "",
                "class": "",
                "id": ""
            },
            "default_value": "",
            "tabs": "all",
            "toolbar": "full",
            "media_upload": 1,
            "delay": 0,
            "acfe_wysiwyg_height": 300,
            "acfe_wysiwyg_max_height": "",
            "acfe_wysiwyg_valid_elements": "",
            "acfe_wysiwyg_custom_style": "",
            "acfe_wysiwyg_disable_wp_style": 0,
            "acfe_wysiwyg_autoresize": 0,
            "acfe_wysiwyg_disable_resize": 0,
            "acfe_wysiwyg_remove_path": 0,
            "acfe_wysiwyg_menubar": 0,
            "acfe_wysiwyg_transparent": 0,
            "acfe_wysiwyg_merge_toolbar": 0,
            "acfe_wysiwyg_custom_toolbar": 0,
            "acfe_field_group_condition": 0
        },
        {
            "key": "field_6217d77369810",
            "label": "Content",
            "name": "event_content",
            "type": "repeater",
            "instructions": "",
            "required": 0,
            "conditional_logic": 0,
            "wrapper": {
                "width": "",
                "class": "",
                "id": ""
            },
            "acfe_repeater_stylised_button": 0,
            "collapsed": "",
            "min": 0,
            "max": 0,
            "layout": "row",
            "button_label": "",
            "acfe_field_group_condition": 0,
            "sub_fields": [
                {
                    "key": "field_6217d77371f0f",
                    "label": "Subtitle",
                    "name": "event_subtitle",
                    "type": "text",
                    "instructions": "",
                    "required": 0,
                    "conditional_logic": 0,
                    "wrapper": {
                        "width": "",
                        "class": "",
                        "id": ""
                    },
                    "default_value": "",
                    "placeholder": "",
                    "prepend": "",
                    "append": "",
                    "maxlength": "",
                    "acfe_field_group_condition": 0
                },
                {
                    "key": "field_6217d77371f66",
                    "label": "Description",
                    "name": "event_description",
                    "type": "wysiwyg",
                    "instructions": "",
                    "required": 0,
                    "conditional_logic": 0,
                    "wrapper": {
                        "width": "",
                        "class": "",
                        "id": ""
                    },
                    "default_value": "",
                    "tabs": "all",
                    "toolbar": "full",
                    "media_upload": 1,
                    "delay": 0,
                    "acfe_wysiwyg_height": 300,
                    "acfe_wysiwyg_max_height": "",
                    "acfe_wysiwyg_valid_elements": "",
                    "acfe_wysiwyg_custom_style": "",
                    "acfe_wysiwyg_disable_wp_style": 0,
                    "acfe_wysiwyg_autoresize": 0,
                    "acfe_wysiwyg_disable_resize": 0,
                    "acfe_wysiwyg_remove_path": 0,
                    "acfe_wysiwyg_menubar": 0,
                    "acfe_wysiwyg_transparent": 0,
                    "acfe_wysiwyg_merge_toolbar": 0,
                    "acfe_wysiwyg_custom_toolbar": 0,
                    "acfe_field_group_condition": 0
                },
                {
                    "key": "field_6217d77371fb4",
                    "label": "External link",
                    "name": "event_external_link",
                    "type": "url",
                    "instructions": "",
                    "required": 0,
                    "conditional_logic": 0,
                    "wrapper": {
                        "width": "",
                        "class": "",
                        "id": ""
                    },
                    "default_value": "",
                    "placeholder": "",
                    "acfe_field_group_condition": 0
                }
            ]
        },
        {
            "key": "field_6217d7736985a",
            "label": "Contenu",
            "name": "event_content_fr",
            "type": "repeater",
            "instructions": "",
            "required": 0,
            "conditional_logic": 0,
            "wrapper": {
                "width": "",
                "class": "",
                "id": ""
            },
            "acfe_repeater_stylised_button": 0,
            "collapsed": "",
            "min": 0,
            "max": 0,
            "layout": "row",
            "button_label": "",
            "acfe_field_group_condition": 0,
            "sub_fields": [
                {
                    "key": "field_6217d7737a823",
                    "label": "Sous-titre",
                    "name": "event_subtitle_fr",
                    "type": "text",
                    "instructions": "",
                    "required": 0,
                    "conditional_logic": 0,
                    "wrapper": {
                        "width": "",
                        "class": "",
                        "id": ""
                    },
                    "default_value": "",
                    "placeholder": "",
                    "prepend": "",
                    "append": "",
                    "maxlength": "",
                    "acfe_field_group_condition": 0
                },
                {
                    "key": "field_6217d7737a872",
                    "label": "Description FR",
                    "name": "event_description_fr",
                    "type": "wysiwyg",
                    "instructions": "",
                    "required": 0,
                    "conditional_logic": 0,
                    "wrapper": {
                        "width": "",
                        "class": "",
                        "id": ""
                    },
                    "default_value": "",
                    "tabs": "all",
                    "toolbar": "full",
                    "media_upload": 1,
                    "delay": 0,
                    "acfe_wysiwyg_height": 300,
                    "acfe_wysiwyg_max_height": "",
                    "acfe_wysiwyg_valid_elements": "",
                    "acfe_wysiwyg_custom_style": "",
                    "acfe_wysiwyg_disable_wp_style": 0,
                    "acfe_wysiwyg_autoresize": 0,
                    "acfe_wysiwyg_disable_resize": 0,
                    "acfe_wysiwyg_remove_path": 0,
                    "acfe_wysiwyg_menubar": 0,
                    "acfe_wysiwyg_transparent": 0,
                    "acfe_wysiwyg_merge_toolbar": 0,
                    "acfe_wysiwyg_custom_toolbar": 0,
                    "acfe_field_group_condition": 0
                },
                {
                    "key": "field_6217d7737a8b7",
                    "label": "Lien externe",
                    "name": "event_external_link_fr",
                    "type": "url",
                    "instructions": "",
                    "required": 0,
                    "conditional_logic": 0,
                    "wrapper": {
                        "width": "",
                        "class": "",
                        "id": ""
                    },
                    "default_value": "",
                    "placeholder": "",
                    "acfe_field_group_condition": 0
                }
            ]
        },
        {
            "key": "field_6217d82978eaf",
            "label": "Gallery photo",
            "name": "event_gallery_photo",
            "type": "text",
            "instructions": "",
            "required": 0,
            "conditional_logic": 0,
            "wrapper": {
                "width": "",
                "class": "",
                "id": ""
            },
            "default_value": "",
            "placeholder": "",
            "prepend": "",
            "append": "",
            "maxlength": "",
            "acfe_field_group_condition": 0
        }
    ],
    "location": [
        [
            {
                "param": "post_type",
                "operator": "==",
                "value": "event"
            }
        ]
    ],
    "menu_order": 0,
    "position": "normal",
    "style": "default",
    "label_placement": "top",
    "instruction_placement": "label",
    "hide_on_screen": "",
    "active": true,
    "description": "",
    "show_in_rest": 0,
    "acfe_autosync": [
        "json"
    ],
    "acfe_form": 0,
    "acfe_display_title": "",
    "acfe_meta": "",
    "acfe_note": "",
    "modified": 1645730442
}